openclean_metanome/__init__.py
openclean_metanome/config.py
openclean_metanome/converter.py
openclean_metanome/download.py
openclean_metanome/tests.py
openclean_metanome/version.py
openclean_metanome/algorithm/__init__.py
openclean_metanome/algorithm/base.py
openclean_metanome/algorithm/hyfd.py
openclean_metanome/algorithm/hyucc.py
openclean_metanome-0.2.0.dist-info/LICENSE
openclean_metanome-0.2.0.dist-info/METADATA
openclean_metanome-0.2.0.dist-info/WHEEL
openclean_metanome-0.2.0.dist-info/top_level.txt
openclean_metanome-0.2.0.dist-info/RECORD
