Metadata-Version: 2.1
Name: openclean-metanome
Version: 0.2.0
Summary: openclean Metanome Python Package
Home-page: https://github.com/VIDA-NYU/openclean-metanome
Author: Heiko Mueller
Author-email: heiko.muller@gmail.com
License: UNKNOWN
Keywords: data cleaning
Platform: UNKNOWN
Classifier: License :: OSI Approved :: BSD License
Classifier: Operating System :: OS Independent
Classifier: Programming Language :: Python :: 3
Classifier: Programming Language :: Python :: 3.7
Classifier: Programming Language :: Python :: 3.8
Classifier: Programming Language :: Python :: 3.9
Classifier: Programming Language :: Python
Requires-Dist: appdirs (>=1.4.4)
Requires-Dist: flowserv-core (>=0.9.0)
Requires-Dist: refdata (>=0.2.0)
Requires-Dist: openclean-core (>=0.4.1)
Provides-Extra: dev
Requires-Dist: coverage (>=4.0) ; extra == 'dev'
Requires-Dist: pytest ; extra == 'dev'
Requires-Dist: pytest-cov ; extra == 'dev'
Requires-Dist: tox ; extra == 'dev'
Requires-Dist: docker ; extra == 'dev'
Requires-Dist: Sphinx ; extra == 'dev'
Requires-Dist: sphinx-rtd-theme ; extra == 'dev'
Requires-Dist: sphinxcontrib-apidoc ; extra == 'dev'
Provides-Extra: docs
Requires-Dist: Sphinx ; extra == 'docs'
Requires-Dist: sphinx-rtd-theme ; extra == 'docs'
Requires-Dist: sphinxcontrib-apidoc ; extra == 'docs'
Provides-Extra: tests
Requires-Dist: coverage (>=4.0) ; extra == 'tests'
Requires-Dist: pytest ; extra == 'tests'
Requires-Dist: pytest-cov ; extra == 'tests'
Requires-Dist: tox ; extra == 'tests'
Requires-Dist: docker ; extra == 'tests'
